atmospy/__init__.py
atmospy/_base.py
atmospy/distributions.py
atmospy/rcmod.py
atmospy/relational.py
atmospy/rose.py
atmospy/stats.py
atmospy/trends.py
atmospy/utils.py
atmospy-0.1.2.dist-info/LICENSE
atmospy-0.1.2.dist-info/METADATA
atmospy-0.1.2.dist-info/WHEEL
atmospy-0.1.2.dist-info/RECORD
