Metadata-Version: 2.1
Name: atmospy
Version: 0.1.2
Summary: Data analysis and visualization for air quality data.
Home-page: https://dhhagan.github.io/atmospy/
License: Apache-2.0
Author: David H Hagan
Author-email: david.hagan@quant-aq.com
Requires-Python: >=3.8,<3.12
Classifier: License :: OSI Approved :: Apache Software License
Classifier: Programming Language :: Python :: 3
Classifier: Programming Language :: Python :: 3.8
Classifier: Programming Language :: Python :: 3.9
Classifier: Programming Language :: Python :: 3.10
Classifier: Programming Language :: Python :: 3.11
Requires-Dist: matplotlib (>=3.4,!=3.6.1)
Requires-Dist: numpy (>=1.20,!=1.24.0)
Requires-Dist: pandas (>=1.2)
Requires-Dist: scipy (>=1.7)
Requires-Dist: seaborn (>=0.12)
Project-URL: Bug Tracker, https://github.com/quant-aq/atmospy/issues
Project-URL: Documentation, https://dhhagan.github.io/atmospy/
Project-URL: Repository, https://github.com/dhhagan/atmospy/
